{
  "actions": [
    "slack_post_message",
    "slack_search_messages"
  ],
  "all_actions": [
    "slack_post_message",
    "slack_search_messages"
  ],
  "authorized": false,
  "available_tools": [],
  "configured": true,
  "display_name": "Slack",
  "last_refreshed": "2025-11-16T07:30:39.171461+00:00",
  "mcp_url": null,
  "provider": "slack",
  "registered": true,
  "tool_count": 2,
  "tools": [
    {
      "available": false,
      "name": "slack_post_message",
      "path": "providers/slack/tools/slack_post_message.json",
      "short_description": "Posts a message to a Slack channel, direct message, or private group; requires content via `text`, `blocks`, or `attachments`"
    },
    {
      "available": false,
      "name": "slack_search_messages",
      "path": "providers/slack/tools/slack_search_messages.json",
      "short_description": "Workspace-wide Slack message search with query modifiers (e.g., `in:#channel`, `from:@user`, `before:YYYY-MM-DD`) plus pagination and sorting controls"
    }
  ]
}
